django_turbolinks-0.5.1.dist-info/DESCRIPTION.rst
django_turbolinks-0.5.1.dist-info/METADATA
django_turbolinks-0.5.1.dist-info/RECORD
django_turbolinks-0.5.1.dist-info/WHEEL
django_turbolinks-0.5.1.dist-info/metadata.json
django_turbolinks-0.5.1.dist-info/top_level.txt
turbolinks/__init__.py
turbolinks/middleware.py
turbolinks/models.py
turbolinks/static/turbolinks/turbolinks.js
