Metadata-Version: 1.1
Name: django-turbolinks
Version: 0.5.1
Summary: Drop-in turbolinks implementation for Django
Home-page: https://github.com/dgladkov/django-turbolinks
Author: Dmitry Gladkov
Author-email: dmitry.gladkov@gmail.com
License: MIT
Platform: UNKNOWN
Classifier: Development Status :: 4 - Beta
Classifier: Environment :: Web Environment
Classifier: Intended Audience :: Developers
Classifier: License :: OSI Approved :: MIT License
Classifier: Operating System :: OS Independent
Classifier: Programming Language :: Python
Classifier: Programming Language :: Python :: 3
Classifier: Topic :: Internet :: WWW/HTTP :: Dynamic Content
Classifier: Topic :: Software Development :: Libraries :: Python Modules
